[
    {
        "id": 3790,
        "registerNumber": "96-149-95",
        "registerYear": 1995,
        "tradeName": "GLYCINE IRRIGATION SOLN 1.5%",
        "scientificName": "GLYCINE",
        "atcCode1": "B05CX03",
        "atcCode2": "",
        "packageSize": 1,
        "size": 1000,
        "strength": "1.5",
        "shelfLife": 24,
        "price": "14.35",
        "drugType": "Generic",
        "packageType": "Bottle",
        "sizeUnit": "ml",
        "strengthUnit": "%",
        "administrationRoute": "Topical",
        "doesageForm": "IRRIGANT",
        "storageConditions": "store below 25°c",
        "marketingStatus": "Marketed",
        "legalStatus": "Prescription",
        "productControl": "Uncontrolled",
        "productControlAr": "غير مقيد",
        "authorizationStatus": "Valid",
        "agent": "Pharmaceutical Solution Industries (PSI)",
        "manufacturerName": "Pharmaceutical Solution Industries (PSI)",
        "manufacturerCountry": "Saudi Arabia",
        "additionalManufacturer": null,
        "additionalManufacturerCountry": null,
        "companyName": "Pharmaceutical Solution Industries (PSI)",
        "legalStatusEn": "Prescription",
        "legalStatusAr": "يحتاج الى وصفة طبية ",
        "domainEN": "Human",
        "domainAR": "بشر",
        "imageUrl": null
    },
    {
        "id": 910,
        "registerNumber": "218-149-00",
        "registerYear": 2000,
        "tradeName": "LIDOCAINE HCL 1% AMPOULE",
        "scientificName": "LIDOCAINE (LIGNOCAINE) HYDROCHLORIDE",
        "atcCode1": "N01BB02",
        "atcCode2": "",
        "packageSize": 1,
        "size": 20,
        "strength": "1",
        "shelfLife": 36,
        "price": "4",
        "drugType": "Generic",
        "packageType": "Ampoule",
        "sizeUnit": "ml",
        "strengthUnit": "%",
        "administrationRoute": "Intravenous",
        "doesageForm": "Solution",
        "storageConditions": "store below 25°c",
        "marketingStatus": "Marketed",
        "legalStatus": "Prescription",
        "productControl": "Uncontrolled",
        "productControlAr": "غير مقيد",
        "authorizationStatus": "Valid",
        "agent": "Pharmaceutical Solution Industries (PSI)",
        "manufacturerName": "Pharmaceutical Solution Industries (PSI)",
        "manufacturerCountry": "Saudi Arabia",
        "additionalManufacturer": null,
        "additionalManufacturerCountry": null,
        "companyName": "Pharmaceutical Solution Industries (PSI)",
        "legalStatusEn": "Prescription",
        "legalStatusAr": "يحتاج الى وصفة طبية ",
        "domainEN": "Human",
        "domainAR": "بشر",
        "imageUrl": null
    },
    {
        "id": 911,
        "registerNumber": "217-149-00",
        "registerYear": 2000,
        "tradeName": "LIDOCAINE HCL 1% AMPOULE",
        "scientificName": "LIDOCAINE (LIGNOCAINE) HYDROCHLORIDE",
        "atcCode1": "N01BB02",
        "atcCode2": "",
        "packageSize": 1,
        "size": 10,
        "strength": "1",
        "shelfLife": 36,
        "price": "3.15",
        "drugType": "Generic",
        "packageType": "Ampoule",
        "sizeUnit": "ml",
        "strengthUnit": "%",
        "administrationRoute": "Intravenous",
        "doesageForm": "Solution",
        "storageConditions": "store below 25°c",
        "marketingStatus": "Marketed",
        "legalStatus": "Prescription",
        "productControl": "Uncontrolled",
        "productControlAr": "غير مقيد",
        "authorizationStatus": "Valid",
        "agent": "Pharmaceutical Solution Industries (PSI)",
        "manufacturerName": "Pharmaceutical Solution Industries (PSI)",
        "manufacturerCountry": "Saudi Arabia",
        "additionalManufacturer": null,
        "additionalManufacturerCountry": null,
        "companyName": "Pharmaceutical Solution Industries (PSI)",
        "legalStatusEn": "Prescription",
        "legalStatusAr": "يحتاج الى وصفة طبية ",
        "domainEN": "Human",
        "domainAR": "بشر",
        "imageUrl": null
    },
    {
        "id": 912,
        "registerNumber": "216-149-00",
        "registerYear": 2000,
        "tradeName": "LIDOCAINE HCL 1% AMPOULE",
        "scientificName": "LIDOCAINE (LIGNOCAINE) HYDROCHLORIDE",
        "atcCode1": "N01BB02",
        "atcCode2": "",
        "packageSize": 1,
        "size": 5,
        "strength": "1",
        "shelfLife": 36,
        "price": "2.75",
        "drugType": "Generic",
        "packageType": "Ampoule",
        "sizeUnit": "ml",
        "strengthUnit": "%",
        "administrationRoute": "Intravenous",
        "doesageForm": "Solution",
        "storageConditions": "store below 25°c",
        "marketingStatus": "Marketed",
        "legalStatus": "Prescription",
        "productControl": "Uncontrolled",
        "productControlAr": "غير مقيد",
        "authorizationStatus": "Valid",
        "agent": "Pharmaceutical Solution Industries (PSI)",
        "manufacturerName": "Pharmaceutical Solution Industries (PSI)",
        "manufacturerCountry": "Saudi Arabia",
        "additionalManufacturer": null,
        "additionalManufacturerCountry": null,
        "companyName": "Pharmaceutical Solution Industries (PSI)",
        "legalStatusEn": "Prescription",
        "legalStatusAr": "يحتاج الى وصفة طبية ",
        "domainEN": "Human",
        "domainAR": "بشر",
        "imageUrl": null
    },
    {
        "id": 3332,
        "registerNumber": "145-149-98",
        "registerYear": 1998,
        "tradeName": "15% W-V POTASSIUM CHLORIDE FOR INJ. USP",
        "scientificName": "POTASSIUM CHLORIDE",
        "atcCode1": "B05XA01",
        "atcCode2": "",
        "packageSize": 1,
        "size": 20,
        "strength": "15",
        "shelfLife": 36,
        "price": "3.3",
        "drugType": "Generic",
        "packageType": "Vial",
        "sizeUnit": "ml",
        "strengthUnit": "%",
        "administrationRoute": "Intravenous",
        "doesageForm": "Solution",
        "storageConditions": "store below 25°c",
        "marketingStatus": "Marketed",
        "legalStatus": "Prescription",
        "productControl": "Uncontrolled",
        "productControlAr": "غير مقيد",
        "authorizationStatus": "Valid",
        "agent": "Pharmaceutical Solution Industries (PSI)",
        "manufacturerName": "Pharmaceutical Solution Industries (PSI)",
        "manufacturerCountry": "Saudi Arabia",
        "additionalManufacturer": null,
        "additionalManufacturerCountry": null,
        "companyName": "Pharmaceutical Solution Industries (PSI)",
        "legalStatusEn": "Prescription",
        "legalStatusAr": "يحتاج الى وصفة طبية ",
        "domainEN": "Human",
        "domainAR": "بشر",
        "imageUrl": null
    },
    {
        "id": 3330,
        "registerNumber": "133-149-96",
        "registerYear": 1996,
        "tradeName": "15% W-V POTASSIUM CHLORIDE FOR INJ. USP",
        "scientificName": "POTASSIUM CHLORIDE",
        "atcCode1": "B05XA01",
        "atcCode2": "",
        "packageSize": 1,
        "size": 5,
        "strength": "15",
        "shelfLife": 36,
        "price": "0.7",
        "drugType": "Generic",
        "packageType": "Vial",
        "sizeUnit": "ml",
        "strengthUnit": "%",
        "administrationRoute": "Intravenous",
        "doesageForm": "Solution",
        "storageConditions": "store below 25°c",
        "marketingStatus": "Marketed",
        "legalStatus": "Prescription",
        "productControl": "Uncontrolled",
        "productControlAr": "غير مقيد",
        "authorizationStatus": "Valid",
        "agent": "Pharmaceutical Solution Industries (PSI)",
        "manufacturerName": "Pharmaceutical Solution Industries (PSI)",
        "manufacturerCountry": "Saudi Arabia",
        "additionalManufacturer": null,
        "additionalManufacturerCountry": null,
        "companyName": "Pharmaceutical Solution Industries (PSI)",
        "legalStatusEn": "Prescription",
        "legalStatusAr": "يحتاج الى وصفة طبية ",
        "domainEN": "Human",
        "domainAR": "بشر",
        "imageUrl": null
    },
    {
        "id": 581,
        "registerNumber": "137-149-97",
        "registerYear": 1997,
        "tradeName": "POTASSIUM CHLORIDE 7.5% AMP",
        "scientificName": "POTASSIUM CHLORIDE",
        "atcCode1": "B05XA01",
        "atcCode2": "",
        "packageSize": 1,
        "size": 20,
        "strength": "7.5",
        "shelfLife": 36,
        "price": "2.6",
        "drugType": "Generic",
        "packageType": "Ampoule",
        "sizeUnit": "ml",
        "strengthUnit": "%",
        "administrationRoute": "Intravenous",
        "doesageForm": "Solution",
        "storageConditions": "store below 25°c",
        "marketingStatus": "Marketed",
        "legalStatus": "Prescription",
        "productControl": "Uncontrolled",
        "productControlAr": "غير مقيد",
        "authorizationStatus": "Valid",
        "agent": "Pharmaceutical Solution Industries (PSI)",
        "manufacturerName": "Pharmaceutical Solution Industries (PSI)",
        "manufacturerCountry": "Saudi Arabia",
        "additionalManufacturer": null,
        "additionalManufacturerCountry": null,
        "companyName": "Pharmaceutical Solution Industries (PSI)",
        "legalStatusEn": "Prescription",
        "legalStatusAr": "يحتاج الى وصفة طبية ",
        "domainEN": "Human",
        "domainAR": "بشر",
        "imageUrl": null
    },
    {
        "id": 582,
        "registerNumber": "146-149-98",
        "registerYear": 1998,
        "tradeName": "POTASSIUM CHLORIDE 7.5% AMP",
        "scientificName": "POTASSIUM CHLORIDE",
        "atcCode1": "B05XA01",
        "atcCode2": "",
        "packageSize": 1,
        "size": 10,
        "strength": "7.5",
        "shelfLife": 36,
        "price": "1.75",
        "drugType": "Generic",
        "packageType": "Ampoule",
        "sizeUnit": "ml",
        "strengthUnit": "%",
        "administrationRoute": "Intravenous",
        "doesageForm": "Solution",
        "storageConditions": "store below 25°c",
        "marketingStatus": "Marketed",
        "legalStatus": "Prescription",
        "productControl": "Uncontrolled",
        "productControlAr": "غير مقيد",
        "authorizationStatus": "Valid",
        "agent": "Pharmaceutical Solution Industries (PSI)",
        "manufacturerName": "Pharmaceutical Solution Industries (PSI)",
        "manufacturerCountry": "Saudi Arabia",
        "additionalManufacturer": null,
        "additionalManufacturerCountry": null,
        "companyName": "Pharmaceutical Solution Industries (PSI)",
        "legalStatusEn": "Prescription",
        "legalStatusAr": "يحتاج الى وصفة طبية ",
        "domainEN": "Human",
        "domainAR": "بشر",
        "imageUrl": null
    },
    {
        "id": 566,
        "registerNumber": "147-149-98",
        "registerYear": 1998,
        "tradeName": "POTASSIUM CHLORIDE 7.5% AMP",
        "scientificName": "POTASSIUM CHLORIDE",
        "atcCode1": "B05XA01",
        "atcCode2": "",
        "packageSize": 1,
        "size": 5,
        "strength": "7.5",
        "shelfLife": 36,
        "price": "1.45",
        "drugType": "Generic",
        "packageType": "Ampoule",
        "sizeUnit": "ml",
        "strengthUnit": "%",
        "administrationRoute": "Intravenous",
        "doesageForm": "Solution",
        "storageConditions": "store below 25°c",
        "marketingStatus": "Marketed",
        "legalStatus": "Prescription",
        "productControl": "Uncontrolled",
        "productControlAr": "غير مقيد",
        "authorizationStatus": "Valid",
        "agent": "Pharmaceutical Solution Industries (PSI)",
        "manufacturerName": "Pharmaceutical Solution Industries (PSI)",
        "manufacturerCountry": "Saudi Arabia",
        "additionalManufacturer": null,
        "additionalManufacturerCountry": null,
        "companyName": "Pharmaceutical Solution Industries (PSI)",
        "legalStatusEn": "Prescription",
        "legalStatusAr": "يحتاج الى وصفة طبية ",
        "domainEN": "Human",
        "domainAR": "بشر",
        "imageUrl": null
    },
    {
        "id": 2853,
        "registerNumber": "164-149-98",
        "registerYear": 1998,
        "tradeName": "DEXTROSE ,RINGER LACTATE",
        "scientificName": "DEXTROSE, LACTATED RINGER'S SOLUTION",
        "atcCode1": "B05BA03",
        "atcCode2": "",
        "packageSize": 1,
        "size": 1000,
        "strength": "5",
        "shelfLife": 48,
        "price": "9.25",
        "drugType": "Generic",
        "packageType": "Bag",
        "sizeUnit": "ml",
        "strengthUnit": "%",
        "administrationRoute": "Intravenous",
        "doesageForm": "Solution",
        "storageConditions": "store below 25°c",
        "marketingStatus": "Marketed",
        "legalStatus": "Prescription",
        "productControl": "Uncontrolled",
        "productControlAr": "غير مقيد",
        "authorizationStatus": "Valid",
        "agent": "Pharmaceutical Solution Industries (PSI)",
        "manufacturerName": "Pharmaceutical Solution Industries (PSI)",
        "manufacturerCountry": "Saudi Arabia",
        "additionalManufacturer": null,
        "additionalManufacturerCountry": null,
        "companyName": "Pharmaceutical Solution Industries (PSI)",
        "legalStatusEn": "Prescription",
        "legalStatusAr": "يحتاج الى وصفة طبية ",
        "domainEN": "Human",
        "domainAR": "بشر",
        "imageUrl": null
    }
]