[
    {
        "id": 9973,
        "registerNumber": "122-124-19",
        "registerYear": 2019,
        "tradeName": "PEDEXA",
        "scientificName": "CELECOXIB",
        "atcCode1": "M01AH01",
        "atcCode2": "",
        "packageSize": 20,
        "size": 0,
        "strength": "100",
        "shelfLife": 36,
        "price": "12.5",
        "drugType": "Generic",
        "packageType": "Blister",
        "sizeUnit": null,
        "strengthUnit": "mg",
        "administrationRoute": "Oral",
        "doesageForm": "Capsule",
        "storageConditions": "store below 30°c",
        "marketingStatus": "Marketed",
        "legalStatus": "Prescription",
        "productControl": "Uncontrolled",
        "productControlAr": "غير مقيد",
        "authorizationStatus": "Valid",
        "agent": "Salehiya Trading Company",
        "manufacturerName": null,
        "manufacturerCountry": null,
        "additionalManufacturer": null,
        "additionalManufacturerCountry": null,
        "companyName": "DAR ALDAWA",
        "legalStatusEn": "Prescription",
        "legalStatusAr": "يحتاج الى وصفة طبية ",
        "domainEN": "Human",
        "domainAR": "بشر",
        "imageUrl": null
    },
    {
        "id": 9976,
        "registerNumber": "123-124-19",
        "registerYear": 2019,
        "tradeName": "PEDEXA",
        "scientificName": "CELECOXIB",
        "atcCode1": "M01AH01",
        "atcCode2": "",
        "packageSize": 10,
        "size": 0,
        "strength": "200",
        "shelfLife": 36,
        "price": "12.5",
        "drugType": "Generic",
        "packageType": "Blister",
        "sizeUnit": null,
        "strengthUnit": "mg",
        "administrationRoute": "Oral",
        "doesageForm": "Capsule",
        "storageConditions": "store below 30°c",
        "marketingStatus": "Marketed",
        "legalStatus": "Prescription",
        "productControl": "Uncontrolled",
        "productControlAr": "غير مقيد",
        "authorizationStatus": "Valid",
        "agent": "Salehiya Trading Company",
        "manufacturerName": null,
        "manufacturerCountry": null,
        "additionalManufacturer": null,
        "additionalManufacturerCountry": null,
        "companyName": "DAR ALDAWA",
        "legalStatusEn": "Prescription",
        "legalStatusAr": "يحتاج الى وصفة طبية ",
        "domainEN": "Human",
        "domainAR": "بشر",
        "imageUrl": null
    },
    {
        "id": 2685,
        "registerNumber": "12-124-92",
        "registerYear": 1992,
        "tradeName": "CEPHADAR CAPSULES 250MG",
        "scientificName": "CEFALEXIN (CEPHALEXIN)",
        "atcCode1": "J01DB01",
        "atcCode2": "",
        "packageSize": 20,
        "size": 0,
        "strength": "250",
        "shelfLife": 36,
        "price": "10.15",
        "drugType": "Generic",
        "packageType": "Blister",
        "sizeUnit": null,
        "strengthUnit": "mg",
        "administrationRoute": "Oral",
        "doesageForm": "Capsule",
        "storageConditions": "store below 30°c",
        "marketingStatus": "Marketed",
        "legalStatus": "Prescription",
        "productControl": "Uncontrolled",
        "productControlAr": "غير مقيد",
        "authorizationStatus": "Valid",
        "agent": "Salehiya Trading Company",
        "manufacturerName": null,
        "manufacturerCountry": null,
        "additionalManufacturer": null,
        "additionalManufacturerCountry": null,
        "companyName": "DAR ALDAWA",
        "legalStatusEn": "Prescription",
        "legalStatusAr": "يحتاج الى وصفة طبية ",
        "domainEN": "Human",
        "domainAR": "بشر",
        "imageUrl": null
    },
    {
        "id": 9491,
        "registerNumber": "5-124-92",
        "registerYear": 1992,
        "tradeName": "MOXIDAD CAPSULES 250MG",
        "scientificName": "AMOXICILLIN",
        "atcCode1": "J01CA04",
        "atcCode2": "",
        "packageSize": 20,
        "size": 0,
        "strength": "250",
        "shelfLife": 48,
        "price": "7.3",
        "drugType": "Generic",
        "packageType": "Blister",
        "sizeUnit": null,
        "strengthUnit": "mg",
        "administrationRoute": "Oral",
        "doesageForm": "Capsule",
        "storageConditions": "store below 25°c",
        "marketingStatus": "Marketed",
        "legalStatus": "Prescription",
        "productControl": "Uncontrolled",
        "productControlAr": "غير مقيد",
        "authorizationStatus": "Valid",
        "agent": "Salehiya Trading Company",
        "manufacturerName": null,
        "manufacturerCountry": null,
        "additionalManufacturer": null,
        "additionalManufacturerCountry": null,
        "companyName": "DAR ALDAWA",
        "legalStatusEn": "Prescription",
        "legalStatusAr": "يحتاج الى وصفة طبية ",
        "domainEN": "Human",
        "domainAR": "بشر",
        "imageUrl": null
    },
    {
        "id": 2616,
        "registerNumber": "49-124-97",
        "registerYear": 1997,
        "tradeName": "CLORACEF FORTE",
        "scientificName": "CEFACLOR",
        "atcCode1": "J01DC04",
        "atcCode2": "",
        "packageSize": 16,
        "size": 0,
        "strength": "500",
        "shelfLife": 36,
        "price": "55.95",
        "drugType": "NCE",
        "packageType": "Blister",
        "sizeUnit": null,
        "strengthUnit": "mg",
        "administrationRoute": "Oral",
        "doesageForm": "Capsule",
        "storageConditions": "store below 25°c",
        "marketingStatus": "Marketed",
        "legalStatus": "Prescription",
        "productControl": "Uncontrolled",
        "productControlAr": "غير مقيد",
        "authorizationStatus": "Valid",
        "agent": "Salehiya Trading Company",
        "manufacturerName": null,
        "manufacturerCountry": null,
        "additionalManufacturer": null,
        "additionalManufacturerCountry": null,
        "companyName": "DAR ALDAWA",
        "legalStatusEn": "Prescription",
        "legalStatusAr": "يحتاج الى وصفة طبية ",
        "domainEN": "Human",
        "domainAR": "بشر",
        "imageUrl": null
    },
    {
        "id": 6089,
        "registerNumber": "34-124-95",
        "registerYear": 1995,
        "tradeName": "DICLOGESIC RETARD",
        "scientificName": "DICLOFENAC SODIUM",
        "atcCode1": "M01AB05",
        "atcCode2": "",
        "packageSize": 10,
        "size": 0,
        "strength": "100",
        "shelfLife": 48,
        "price": "9.05",
        "drugType": "Generic",
        "packageType": "Blister",
        "sizeUnit": null,
        "strengthUnit": "mg",
        "administrationRoute": "Oral",
        "doesageForm": "Capsule",
        "storageConditions": "store below 25°c",
        "marketingStatus": "Marketed",
        "legalStatus": "Prescription",
        "productControl": "Uncontrolled",
        "productControlAr": "غير مقيد",
        "authorizationStatus": "Valid",
        "agent": "Salehiya Trading Company",
        "manufacturerName": null,
        "manufacturerCountry": null,
        "additionalManufacturer": null,
        "additionalManufacturerCountry": null,
        "companyName": "DAR ALDAWA",
        "legalStatusEn": "Prescription",
        "legalStatusAr": "يحتاج الى وصفة طبية ",
        "domainEN": "Human",
        "domainAR": "بشر",
        "imageUrl": null
    },
    {
        "id": 4452,
        "registerNumber": "27-124-89",
        "registerYear": 1989,
        "tradeName": "DICLOGESIC",
        "scientificName": "DICLOFENAC SODIUM",
        "atcCode1": "M01AB05",
        "atcCode2": "",
        "packageSize": 5,
        "size": 0,
        "strength": "12.5",
        "shelfLife": 36,
        "price": "11.4",
        "drugType": "Generic",
        "packageType": "Blister",
        "sizeUnit": null,
        "strengthUnit": "mg",
        "administrationRoute": "Rectal",
        "doesageForm": "suppository",
        "storageConditions": "store below 30°c",
        "marketingStatus": "Marketed",
        "legalStatus": "Prescription",
        "productControl": "Uncontrolled",
        "productControlAr": "غير مقيد",
        "authorizationStatus": "Valid",
        "agent": "Salehiya Trading Company",
        "manufacturerName": null,
        "manufacturerCountry": null,
        "additionalManufacturer": null,
        "additionalManufacturerCountry": null,
        "companyName": "DAR ALDAWA",
        "legalStatusEn": "Prescription",
        "legalStatusAr": "يحتاج الى وصفة طبية ",
        "domainEN": "Human",
        "domainAR": "بشر",
        "imageUrl": null
    },
    {
        "id": 1208,
        "registerNumber": "57-124-00",
        "registerYear": 2000,
        "tradeName": "MYCOHEAL 200MG VAGINAL SUPPOSITORY",
        "scientificName": "MICONAZOLE",
        "atcCode1": "G01AF04",
        "atcCode2": "",
        "packageSize": 7,
        "size": 0,
        "strength": "200",
        "shelfLife": 24,
        "price": "13.55",
        "drugType": "Generic",
        "packageType": "Blister",
        "sizeUnit": null,
        "strengthUnit": "mg",
        "administrationRoute": "Vaginal",
        "doesageForm": "suppository",
        "storageConditions": "store below 30°c",
        "marketingStatus": "Marketed",
        "legalStatus": "Prescription",
        "productControl": "Uncontrolled",
        "productControlAr": "غير مقيد",
        "authorizationStatus": "Valid",
        "agent": "Salehiya Trading Company",
        "manufacturerName": null,
        "manufacturerCountry": null,
        "additionalManufacturer": null,
        "additionalManufacturerCountry": null,
        "companyName": "DAR ALDAWA",
        "legalStatusEn": "Prescription",
        "legalStatusAr": "يحتاج الى وصفة طبية ",
        "domainEN": "Human",
        "domainAR": "بشر",
        "imageUrl": null
    },
    {
        "id": 1200,
        "registerNumber": "37-124-95",
        "registerYear": 1995,
        "tradeName": "MYCOHEAL 400MG VAGINAL SUPPOSITORIES",
        "scientificName": "MICONAZOLE",
        "atcCode1": "G01AF04",
        "atcCode2": "",
        "packageSize": 3,
        "size": 0,
        "strength": "400",
        "shelfLife": 36,
        "price": "12.25",
        "drugType": "Generic",
        "packageType": "Blister",
        "sizeUnit": null,
        "strengthUnit": "mg",
        "administrationRoute": "Vaginal",
        "doesageForm": "suppository",
        "storageConditions": "store below 30°c",
        "marketingStatus": "Marketed",
        "legalStatus": "Prescription",
        "productControl": "Uncontrolled",
        "productControlAr": "غير مقيد",
        "authorizationStatus": "Valid",
        "agent": "Salehiya Trading Company",
        "manufacturerName": null,
        "manufacturerCountry": null,
        "additionalManufacturer": null,
        "additionalManufacturerCountry": null,
        "companyName": "DAR ALDAWA",
        "legalStatusEn": "Prescription",
        "legalStatusAr": "يحتاج الى وصفة طبية ",
        "domainEN": "Human",
        "domainAR": "بشر",
        "imageUrl": null
    },
    {
        "id": 6685,
        "registerNumber": "78-124-08",
        "registerYear": 2008,
        "tradeName": "ANXETIN 20MG CAPSULES",
        "scientificName": "FLUOXETINE",
        "atcCode1": "N06AB03",
        "atcCode2": "",
        "packageSize": 20,
        "size": 0,
        "strength": "20",
        "shelfLife": 36,
        "price": "37.65",
        "drugType": "Generic",
        "packageType": "Blister",
        "sizeUnit": null,
        "strengthUnit": "mg",
        "administrationRoute": "Oral",
        "doesageForm": "Capsule",
        "storageConditions": "store below 30°c",
        "marketingStatus": "Marketed",
        "legalStatus": "Prescription",
        "productControl": "Uncontrolled",
        "productControlAr": "غير مقيد",
        "authorizationStatus": "Valid",
        "agent": "Salehiya Trading Company",
        "manufacturerName": null,
        "manufacturerCountry": null,
        "additionalManufacturer": null,
        "additionalManufacturerCountry": null,
        "companyName": "DAR ALDAWA",
        "legalStatusEn": "Prescription",
        "legalStatusAr": "يحتاج الى وصفة طبية ",
        "domainEN": "Human",
        "domainAR": "بشر",
        "imageUrl": null
    }
]