[
    {
        "id": 9235,
        "registerNumber": "31-5223-19",
        "registerYear": 2019,
        "tradeName": "IMOZET 3.5MG POWDER FOR SOLUTION FOR INJECTION",
        "scientificName": "BORTEZOMIB",
        "atcCode1": "L01XX32 ",
        "atcCode2": "",
        "packageSize": 1,
        "size": 10,
        "strength": "3.5",
        "shelfLife": 36,
        "price": "2418.95",
        "drugType": "Generic",
        "packageType": "Vial",
        "sizeUnit": "ml",
        "strengthUnit": "mg",
        "administrationRoute": "SUBCUTANEOUS, INTRAVENOUS",
        "doesageForm": "POWDER, FOR SOLUTION",
        "storageConditions": "store below 30°c",
        "marketingStatus": "Marketed",
        "legalStatus": "Prescription",
        "productControl": "Uncontrolled",
        "productControlAr": "غير مقيد",
        "authorizationStatus": "Valid",
        "agent": "Zimmo Trading Company Ltd",
        "manufacturerName": null,
        "manufacturerCountry": null,
        "additionalManufacturer": null,
        "additionalManufacturerCountry": null,
        "companyName": null,
        "legalStatusEn": "Prescription",
        "legalStatusAr": "يحتاج الى وصفة طبية ",
        "domainEN": "Human",
        "domainAR": "بشر",
        "imageUrl": null
    },
    {
        "id": 9192,
        "registerNumber": "29-5223-19",
        "registerYear": 2019,
        "tradeName": "TINPLAT 1 mg/ml VIAL",
        "scientificName": "CISPLATIN",
        "atcCode1": "L01XA01",
        "atcCode2": "",
        "packageSize": 1,
        "size": 10,
        "strength": "1",
        "shelfLife": 24,
        "price": "21",
        "drugType": "Generic",
        "packageType": "Vial",
        "sizeUnit": "ml",
        "strengthUnit": "mg/ml",
        "administrationRoute": "Intravenous",
        "doesageForm": "INJECTION, SOLUTION, CONCENTRATE",
        "storageConditions": "store below 30°c",
        "marketingStatus": "Marketed",
        "legalStatus": "Prescription",
        "productControl": "Uncontrolled",
        "productControlAr": "غير مقيد",
        "authorizationStatus": "Valid",
        "agent": "Zimmo Trading Company Ltd",
        "manufacturerName": null,
        "manufacturerCountry": null,
        "additionalManufacturer": null,
        "additionalManufacturerCountry": null,
        "companyName": null,
        "legalStatusEn": "Prescription",
        "legalStatusAr": "يحتاج الى وصفة طبية ",
        "domainEN": "Human",
        "domainAR": "بشر",
        "imageUrl": null
    },
    {
        "id": 9220,
        "registerNumber": "30-5223-19",
        "registerYear": 2019,
        "tradeName": "TINPLAT 1 mg/ml VIAL",
        "scientificName": "CISPLATIN",
        "atcCode1": "L01XA01",
        "atcCode2": "",
        "packageSize": 1,
        "size": 50,
        "strength": "1",
        "shelfLife": 24,
        "price": "60",
        "drugType": "Generic",
        "packageType": "Vial",
        "sizeUnit": "ml",
        "strengthUnit": "mg/ml",
        "administrationRoute": "Intravenous",
        "doesageForm": "INJECTION, SOLUTION, CONCENTRATE",
        "storageConditions": "store below 30°c",
        "marketingStatus": "Marketed",
        "legalStatus": "Prescription",
        "productControl": "Uncontrolled",
        "productControlAr": "غير مقيد",
        "authorizationStatus": "Valid",
        "agent": "Zimmo Trading Company Ltd",
        "manufacturerName": null,
        "manufacturerCountry": null,
        "additionalManufacturer": null,
        "additionalManufacturerCountry": null,
        "companyName": null,
        "legalStatusEn": "Prescription",
        "legalStatusAr": "يحتاج الى وصفة طبية ",
        "domainEN": "Human",
        "domainAR": "بشر",
        "imageUrl": null
    },
    {
        "id": 9078,
        "registerNumber": "22-5223-19",
        "registerYear": 2019,
        "tradeName": "CARTINUM 10 MG/ML VIAL",
        "scientificName": "CARBOPLATIN",
        "atcCode1": "L01XA02",
        "atcCode2": "",
        "packageSize": 1,
        "size": 45,
        "strength": "10",
        "shelfLife": 24,
        "price": "208.3",
        "drugType": "Generic",
        "packageType": "Vial",
        "sizeUnit": "ml",
        "strengthUnit": "mg/ml",
        "administrationRoute": "Intravenous",
        "doesageForm": "INJECTION, SOLUTION, CONCENTRATE",
        "storageConditions": "store below 30°c",
        "marketingStatus": "Marketed",
        "legalStatus": "Prescription",
        "productControl": "Uncontrolled",
        "productControlAr": "غير مقيد",
        "authorizationStatus": "Valid",
        "agent": "Zimmo Trading Company Ltd",
        "manufacturerName": null,
        "manufacturerCountry": null,
        "additionalManufacturer": null,
        "additionalManufacturerCountry": null,
        "companyName": null,
        "legalStatusEn": "Prescription",
        "legalStatusAr": "يحتاج الى وصفة طبية ",
        "domainEN": "Human",
        "domainAR": "بشر",
        "imageUrl": null
    },
    {
        "id": 9071,
        "registerNumber": "21-5223-19",
        "registerYear": 2019,
        "tradeName": "CARTINUM 150 MG/15 ML",
        "scientificName": "CARBOPLATIN",
        "atcCode1": "L01XA02",
        "atcCode2": "",
        "packageSize": 1,
        "size": 15,
        "strength": "10",
        "shelfLife": 24,
        "price": "69.45",
        "drugType": "Generic",
        "packageType": "Vial",
        "sizeUnit": "ml",
        "strengthUnit": "mg/ml",
        "administrationRoute": "Intravenous",
        "doesageForm": "INJECTION, SOLUTION, CONCENTRATE",
        "storageConditions": "store below 30°c",
        "marketingStatus": "Marketed",
        "legalStatus": "Prescription",
        "productControl": "Uncontrolled",
        "productControlAr": "غير مقيد",
        "authorizationStatus": "Valid",
        "agent": "Zimmo Trading Company Ltd",
        "manufacturerName": null,
        "manufacturerCountry": null,
        "additionalManufacturer": null,
        "additionalManufacturerCountry": null,
        "companyName": null,
        "legalStatusEn": "Prescription",
        "legalStatusAr": "يحتاج الى وصفة طبية ",
        "domainEN": "Human",
        "domainAR": "بشر",
        "imageUrl": null
    },
    {
        "id": 2181,
        "registerNumber": "1-470-08",
        "registerYear": 2008,
        "tradeName": "RHOPHYLAC 300MCG-2ML SOL. FOR INJ.IN PFS",
        "scientificName": "ANTI-D (RH0) IMMUNOGLOBULIN",
        "atcCode1": "J06BB01",
        "atcCode2": "",
        "packageSize": 1,
        "size": 0,
        "strength": "300",
        "shelfLife": 36,
        "price": "228.75",
        "drugType": "Biological",
        "packageType": "Injection Syringe",
        "sizeUnit": null,
        "strengthUnit": "µg",
        "administrationRoute": "Intravenous",
        "doesageForm": "Solution",
        "storageConditions": "store in a refrigerator (2°c – 8°c)",
        "marketingStatus": "Marketed",
        "legalStatus": "Prescription",
        "productControl": "Uncontrolled",
        "productControlAr": "غير مقيد",
        "authorizationStatus": "Valid",
        "agent": "Zimmo Trading Company Ltd",
        "manufacturerName": null,
        "manufacturerCountry": null,
        "additionalManufacturer": null,
        "additionalManufacturerCountry": null,
        "companyName": null,
        "legalStatusEn": "Prescription",
        "legalStatusAr": "يحتاج الى وصفة طبية ",
        "domainEN": "Human",
        "domainAR": "بشر",
        "imageUrl": null
    },
    {
        "id": 6965,
        "registerNumber": "5-470-15",
        "registerYear": 2015,
        "tradeName": "HUMAN ALBUMIN 200 g/l solution for infusion",
        "scientificName": "ALBUMIN (HUMAN ALBUMIN SOLUTION)",
        "atcCode1": "B05AA01",
        "atcCode2": "",
        "packageSize": 1,
        "size": 100,
        "strength": "200",
        "shelfLife": 36,
        "price": "249.1",
        "drugType": "Biological",
        "packageType": "Vial",
        "sizeUnit": "ml",
        "strengthUnit": "g/l",
        "administrationRoute": "Intravenous",
        "doesageForm": "Solution",
        "storageConditions": "do not store above 25°c",
        "marketingStatus": "Marketed",
        "legalStatus": "Prescription",
        "productControl": "Uncontrolled",
        "productControlAr": "غير مقيد",
        "authorizationStatus": "Valid",
        "agent": "Zimmo Trading Company Ltd",
        "manufacturerName": null,
        "manufacturerCountry": null,
        "additionalManufacturer": null,
        "additionalManufacturerCountry": null,
        "companyName": null,
        "legalStatusEn": "Prescription",
        "legalStatusAr": "يحتاج الى وصفة طبية ",
        "domainEN": "Human",
        "domainAR": "بشر",
        "imageUrl": null
    },
    {
        "id": 6966,
        "registerNumber": "6-470-15",
        "registerYear": 2015,
        "tradeName": "HUMAN ALBUMIN 200 g/l solution for infusion",
        "scientificName": "ALBUMIN (HUMAN ALBUMIN SOLUTION)",
        "atcCode1": "B05AA01",
        "atcCode2": "",
        "packageSize": 1,
        "size": 50,
        "strength": "200",
        "shelfLife": 36,
        "price": "154.95",
        "drugType": "Biological",
        "packageType": "Vial",
        "sizeUnit": "ml",
        "strengthUnit": "g/l",
        "administrationRoute": "Intravenous",
        "doesageForm": "Solution",
        "storageConditions": "do not store above 25°c",
        "marketingStatus": "Marketed",
        "legalStatus": "Prescription",
        "productControl": "Uncontrolled",
        "productControlAr": "غير مقيد",
        "authorizationStatus": "Valid",
        "agent": "Zimmo Trading Company Ltd",
        "manufacturerName": null,
        "manufacturerCountry": null,
        "additionalManufacturer": null,
        "additionalManufacturerCountry": null,
        "companyName": null,
        "legalStatusEn": "Prescription",
        "legalStatusAr": "يحتاج الى وصفة طبية ",
        "domainEN": "Human",
        "domainAR": "بشر",
        "imageUrl": null
    },
    {
        "id": 9253,
        "registerNumber": "32-5223-19",
        "registerYear": 2019,
        "tradeName": "ONDRON 2MG/ML AMPOULE",
        "scientificName": "ONDANSETRON",
        "atcCode1": "A04AA01 ",
        "atcCode2": "",
        "packageSize": 5,
        "size": 4,
        "strength": "2",
        "shelfLife": 36,
        "price": "112.25",
        "drugType": "Generic",
        "packageType": "Ampoule",
        "sizeUnit": "ml",
        "strengthUnit": "mg/ml",
        "administrationRoute": "INTRAMUSCULAR, INTRAVENOUS",
        "doesageForm": "Solution",
        "storageConditions": "store below 30°c",
        "marketingStatus": "Marketed",
        "legalStatus": "Prescription",
        "productControl": "Uncontrolled",
        "productControlAr": "غير مقيد",
        "authorizationStatus": "Valid",
        "agent": "Zimmo Trading Company Ltd",
        "manufacturerName": null,
        "manufacturerCountry": null,
        "additionalManufacturer": null,
        "additionalManufacturerCountry": null,
        "companyName": null,
        "legalStatusEn": "Prescription",
        "legalStatusAr": "يحتاج الى وصفة طبية ",
        "domainEN": "Human",
        "domainAR": "بشر",
        "imageUrl": null
    },
    {
        "id": 9270,
        "registerNumber": "33-5223-19",
        "registerYear": 2019,
        "tradeName": "ONDRON 2MG/ML AMPOULE",
        "scientificName": "ONDANSETRON",
        "atcCode1": "A04AA01 ",
        "atcCode2": "",
        "packageSize": 5,
        "size": 2,
        "strength": "2",
        "shelfLife": 36,
        "price": "56.1",
        "drugType": "Generic",
        "packageType": "Ampoule",
        "sizeUnit": "ml",
        "strengthUnit": "mg/ml",
        "administrationRoute": "INTRAMUSCULAR, INTRAVENOUS",
        "doesageForm": "Solution",
        "storageConditions": "store below 30°c",
        "marketingStatus": "Marketed",
        "legalStatus": "Prescription",
        "productControl": "Uncontrolled",
        "productControlAr": "غير مقيد",
        "authorizationStatus": "Valid",
        "agent": "Zimmo Trading Company Ltd",
        "manufacturerName": null,
        "manufacturerCountry": null,
        "additionalManufacturer": null,
        "additionalManufacturerCountry": null,
        "companyName": null,
        "legalStatusEn": "Prescription",
        "legalStatusAr": "يحتاج الى وصفة طبية ",
        "domainEN": "Human",
        "domainAR": "بشر",
        "imageUrl": null
    }
]