[
    {
        "id": 3990,
        "registerNumber": "141-212-01",
        "registerYear": 2001,
        "tradeName": "GLAZE 80MG TAB",
        "scientificName": "GLICLAZIDE",
        "atcCode1": "A10BB09",
        "atcCode2": "",
        "packageSize": 60,
        "size": 0,
        "strength": "80",
        "shelfLife": 36,
        "price": "34.95",
        "drugType": "Generic",
        "packageType": "Blister",
        "sizeUnit": null,
        "strengthUnit": "mg",
        "administrationRoute": "Oral",
        "doesageForm": "Tablet",
        "storageConditions": "store below 30°c",
        "marketingStatus": "Marketed",
        "legalStatus": "Prescription",
        "productControl": "Uncontrolled",
        "productControlAr": "غير مقيد",
        "authorizationStatus": "Valid",
        "agent": "SPIMACO",
        "manufacturerName": null,
        "manufacturerCountry": null,
        "additionalManufacturer": null,
        "additionalManufacturerCountry": null,
        "companyName": "SPIMACO",
        "legalStatusEn": "Prescription",
        "legalStatusAr": "يحتاج الى وصفة طبية ",
        "domainEN": "Human",
        "domainAR": "بشر",
        "imageUrl": null
    },
    {
        "id": 3991,
        "registerNumber": "140-212-01",
        "registerYear": 2001,
        "tradeName": "GLAZE 80MG TAB",
        "scientificName": "GLICLAZIDE",
        "atcCode1": "A10BB09",
        "atcCode2": "",
        "packageSize": 20,
        "size": 0,
        "strength": "80",
        "shelfLife": 36,
        "price": "13.25",
        "drugType": "Generic",
        "packageType": "Blister",
        "sizeUnit": null,
        "strengthUnit": "mg",
        "administrationRoute": "Oral",
        "doesageForm": "Tablet",
        "storageConditions": "store below 30°c",
        "marketingStatus": "Marketed",
        "legalStatus": "Prescription",
        "productControl": "Uncontrolled",
        "productControlAr": "غير مقيد",
        "authorizationStatus": "Valid",
        "agent": "SPIMACO",
        "manufacturerName": null,
        "manufacturerCountry": null,
        "additionalManufacturer": null,
        "additionalManufacturerCountry": null,
        "companyName": "SPIMACO",
        "legalStatusEn": "Prescription",
        "legalStatusAr": "يحتاج الى وصفة طبية ",
        "domainEN": "Human",
        "domainAR": "بشر",
        "imageUrl": null
    },
    {
        "id": 1336,
        "registerNumber": "176-212-02",
        "registerYear": 2002,
        "tradeName": "VERINE 135MG TAB",
        "scientificName": "MEBEVERINE HYDROCHLORIDE",
        "atcCode1": "A03AA04",
        "atcCode2": "",
        "packageSize": 30,
        "size": 0,
        "strength": "135",
        "shelfLife": 36,
        "price": "19.45",
        "drugType": "Generic",
        "packageType": "Blister",
        "sizeUnit": null,
        "strengthUnit": "mg",
        "administrationRoute": "Oral",
        "doesageForm": "Tablet",
        "storageConditions": "store below 30°c",
        "marketingStatus": "Marketed",
        "legalStatus": "Prescription",
        "productControl": "Uncontrolled",
        "productControlAr": "غير مقيد",
        "authorizationStatus": "Valid",
        "agent": "SPIMACO",
        "manufacturerName": null,
        "manufacturerCountry": null,
        "additionalManufacturer": null,
        "additionalManufacturerCountry": null,
        "companyName": "SPIMACO",
        "legalStatusEn": "Prescription",
        "legalStatusAr": "يحتاج الى وصفة طبية ",
        "domainEN": "Human",
        "domainAR": "بشر",
        "imageUrl": null
    },
    {
        "id": 7757,
        "registerNumber": "328-212-16",
        "registerYear": 2016,
        "tradeName": "ZOLINDA 10 mg tablet",
        "scientificName": "ARIPIPRAZOLE",
        "atcCode1": "N05AX12",
        "atcCode2": "",
        "packageSize": 30,
        "size": 0,
        "strength": "10",
        "shelfLife": 24,
        "price": "274.4",
        "drugType": "Generic",
        "packageType": "Blister",
        "sizeUnit": null,
        "strengthUnit": "mg",
        "administrationRoute": "Oral",
        "doesageForm": "Tablet",
        "storageConditions": "store below 30°c",
        "marketingStatus": "Marketed",
        "legalStatus": "Prescription",
        "productControl": "Uncontrolled",
        "productControlAr": "غير مقيد",
        "authorizationStatus": "Valid",
        "agent": "SPIMACO",
        "manufacturerName": null,
        "manufacturerCountry": null,
        "additionalManufacturer": null,
        "additionalManufacturerCountry": null,
        "companyName": "SPIMACO",
        "legalStatusEn": "Prescription",
        "legalStatusAr": "يحتاج الى وصفة طبية ",
        "domainEN": "Human",
        "domainAR": "بشر",
        "imageUrl": null
    },
    {
        "id": 7758,
        "registerNumber": "329-212-16",
        "registerYear": 2016,
        "tradeName": "ZOLINDA 5 mg tablet",
        "scientificName": "ARIPIPRAZOLE",
        "atcCode1": "N05AX12",
        "atcCode2": "",
        "packageSize": 30,
        "size": 0,
        "strength": "5",
        "shelfLife": 24,
        "price": "137.2",
        "drugType": "Generic",
        "packageType": "Blister",
        "sizeUnit": null,
        "strengthUnit": "mg",
        "administrationRoute": "Oral",
        "doesageForm": "Tablet",
        "storageConditions": "store below 30°c",
        "marketingStatus": "Marketed",
        "legalStatus": "Prescription",
        "productControl": "Uncontrolled",
        "productControlAr": "غير مقيد",
        "authorizationStatus": "Valid",
        "agent": "SPIMACO",
        "manufacturerName": null,
        "manufacturerCountry": null,
        "additionalManufacturer": null,
        "additionalManufacturerCountry": null,
        "companyName": "SPIMACO",
        "legalStatusEn": "Prescription",
        "legalStatusAr": "يحتاج الى وصفة طبية ",
        "domainEN": "Human",
        "domainAR": "بشر",
        "imageUrl": null
    },
    {
        "id": 7759,
        "registerNumber": "330-212-16",
        "registerYear": 2016,
        "tradeName": "ZOLINDA 15 mg tablet",
        "scientificName": "ARIPIPRAZOLE",
        "atcCode1": "N05AX12",
        "atcCode2": "",
        "packageSize": 30,
        "size": 0,
        "strength": "15",
        "shelfLife": 24,
        "price": "340.9",
        "drugType": "Generic",
        "packageType": "Blister",
        "sizeUnit": null,
        "strengthUnit": "mg",
        "administrationRoute": "Oral",
        "doesageForm": "Tablet",
        "storageConditions": "store below 30°c",
        "marketingStatus": "Marketed",
        "legalStatus": "Prescription",
        "productControl": "Uncontrolled",
        "productControlAr": "غير مقيد",
        "authorizationStatus": "Valid",
        "agent": "SPIMACO",
        "manufacturerName": null,
        "manufacturerCountry": null,
        "additionalManufacturer": null,
        "additionalManufacturerCountry": null,
        "companyName": "SPIMACO",
        "legalStatusEn": "Prescription",
        "legalStatusAr": "يحتاج الى وصفة طبية ",
        "domainEN": "Human",
        "domainAR": "بشر",
        "imageUrl": null
    },
    {
        "id": 1961,
        "registerNumber": "106-212-99",
        "registerYear": 1999,
        "tradeName": "SAPOFEN 600 MG TAB",
        "scientificName": "IBUPROFEN",
        "atcCode1": "M01AE01",
        "atcCode2": "",
        "packageSize": 30,
        "size": 0,
        "strength": "600",
        "shelfLife": 48,
        "price": "14.5",
        "drugType": "Generic",
        "packageType": "Blister",
        "sizeUnit": null,
        "strengthUnit": "mg",
        "administrationRoute": "Oral",
        "doesageForm": "Tablet",
        "storageConditions": "store below 30°c",
        "marketingStatus": "Marketed",
        "legalStatus": "Prescription",
        "productControl": "Uncontrolled",
        "productControlAr": "غير مقيد",
        "authorizationStatus": "Valid",
        "agent": "SPIMACO",
        "manufacturerName": null,
        "manufacturerCountry": null,
        "additionalManufacturer": null,
        "additionalManufacturerCountry": null,
        "companyName": "SPIMACO",
        "legalStatusEn": "Prescription",
        "legalStatusAr": "يحتاج الى وصفة طبية ",
        "domainEN": "Human",
        "domainAR": "بشر",
        "imageUrl": null
    },
    {
        "id": 4705,
        "registerNumber": "53-212-97",
        "registerYear": 1997,
        "tradeName": "FEVADOL PLUS TAB",
        "scientificName": "PARACETAMOL, CAFFEINE, CODEINE PHOSPHATE",
        "atcCode1": "N02BE51",
        "atcCode2": "",
        "packageSize": 20,
        "size": 0,
        "strength": "500, 30, 8",
        "shelfLife": 60,
        "price": "7.7",
        "drugType": "Generic",
        "packageType": "Blister",
        "sizeUnit": null,
        "strengthUnit": "mg",
        "administrationRoute": "Oral",
        "doesageForm": "Tablet",
        "storageConditions": "store below 30°c",
        "marketingStatus": "Marketed",
        "legalStatus": "Prescription",
        "productControl": "Uncontrolled",
        "productControlAr": "غير مقيد",
        "authorizationStatus": "Valid",
        "agent": "SPIMACO",
        "manufacturerName": null,
        "manufacturerCountry": null,
        "additionalManufacturer": null,
        "additionalManufacturerCountry": null,
        "companyName": "SPIMACO",
        "legalStatusEn": "Prescription",
        "legalStatusAr": "يحتاج الى وصفة طبية ",
        "domainEN": "Human",
        "domainAR": "بشر",
        "imageUrl": null
    },
    {
        "id": 8302,
        "registerNumber": "404-212-18",
        "registerYear": 2018,
        "tradeName": "VALDATIN 50MG TABLET",
        "scientificName": "VILDAGLIPTIN",
        "atcCode1": "A10BH02",
        "atcCode2": "",
        "packageSize": 28,
        "size": 0,
        "strength": "50",
        "shelfLife": 24,
        "price": "33.25",
        "drugType": "Generic",
        "packageType": "Blister",
        "sizeUnit": null,
        "strengthUnit": "mg",
        "administrationRoute": "Oral",
        "doesageForm": "Tablet",
        "storageConditions": "store below 30°c",
        "marketingStatus": "Marketed",
        "legalStatus": "Prescription",
        "productControl": "Uncontrolled",
        "productControlAr": "غير مقيد",
        "authorizationStatus": "Valid",
        "agent": "SPIMACO",
        "manufacturerName": null,
        "manufacturerCountry": null,
        "additionalManufacturer": null,
        "additionalManufacturerCountry": null,
        "companyName": "SPIMACO",
        "legalStatusEn": "Prescription",
        "legalStatusAr": "يحتاج الى وصفة طبية ",
        "domainEN": "Human",
        "domainAR": "بشر",
        "imageUrl": null
    },
    {
        "id": 8303,
        "registerNumber": "405-212-18",
        "registerYear": 2018,
        "tradeName": "VALDATIN 50MG TABLET",
        "scientificName": "VILDAGLIPTIN",
        "atcCode1": "A10BH03",
        "atcCode2": "",
        "packageSize": 56,
        "size": 0,
        "strength": "50",
        "shelfLife": 24,
        "price": "66.5",
        "drugType": "Generic",
        "packageType": "Blister",
        "sizeUnit": null,
        "strengthUnit": "mg",
        "administrationRoute": "Oral",
        "doesageForm": "Tablet",
        "storageConditions": "store below 30°c",
        "marketingStatus": "Marketed",
        "legalStatus": "Prescription",
        "productControl": "Uncontrolled",
        "productControlAr": "غير مقيد",
        "authorizationStatus": "Valid",
        "agent": "SPIMACO",
        "manufacturerName": null,
        "manufacturerCountry": null,
        "additionalManufacturer": null,
        "additionalManufacturerCountry": null,
        "companyName": "SPIMACO",
        "legalStatusEn": "Prescription",
        "legalStatusAr": "يحتاج الى وصفة طبية ",
        "domainEN": "Human",
        "domainAR": "بشر",
        "imageUrl": null
    }
]