[
    {
        "id": 3608,
        "registerNumber": "21-437-14",
        "registerYear": 2014,
        "tradeName": "Avocom-M Cream",
        "scientificName": "MOMETASONE FUROATE, MICONAZOLE",
        "atcCode1": "D01AC52",
        "atcCode2": "",
        "packageSize": 1,
        "size": 30,
        "strength": "0.1, 2",
        "shelfLife": 24,
        "price": "23",
        "drugType": "Generic",
        "packageType": "Tube",
        "sizeUnit": "g",
        "strengthUnit": "%",
        "administrationRoute": "Topical",
        "doesageForm": "cream",
        "storageConditions": "store below 30°c",
        "marketingStatus": "Marketed",
        "legalStatus": "Prescription",
        "productControl": "Uncontrolled",
        "productControlAr": "غير مقيد",
        "authorizationStatus": "Valid",
        "agent": "Middle East Pharmaceutical Industries Co. Ltd. (MECP)",
        "manufacturerName": "Middle East Pharmaceutical Industries Co. Ltd. (MECP)",
        "manufacturerCountry": "Saudi Arabia",
        "additionalManufacturer": null,
        "additionalManufacturerCountry": null,
        "companyName": "Middle East Pharmaceutical Industries Co. Ltd. (MECP)",
        "legalStatusEn": "Prescription",
        "legalStatusAr": "يحتاج الى وصفة طبية ",
        "domainEN": "Human",
        "domainAR": "بشر",
        "imageUrl": null
    },
    {
        "id": 6951,
        "registerNumber": "29-437-16",
        "registerYear": 2016,
        "tradeName": "LYRGABA 75 mg capsule",
        "scientificName": "PREGABALIN",
        "atcCode1": "N03AX16",
        "atcCode2": "",
        "packageSize": 40,
        "size": 0,
        "strength": "75",
        "shelfLife": 24,
        "price": "85.6",
        "drugType": "Generic",
        "packageType": "Blister",
        "sizeUnit": null,
        "strengthUnit": "mg",
        "administrationRoute": "Oral",
        "doesageForm": "Capsule",
        "storageConditions": "store below 30°c",
        "marketingStatus": "Marketed",
        "legalStatus": "Prescription",
        "productControl": "Controlled",
        "productControlAr": "مقيد",
        "authorizationStatus": "Valid",
        "agent": "Middle East Pharmaceutical Industries Co. Ltd. (MECP)",
        "manufacturerName": "Middle East Pharmaceutical Industries Co. Ltd. (MECP)",
        "manufacturerCountry": "Saudi Arabia",
        "additionalManufacturer": null,
        "additionalManufacturerCountry": null,
        "companyName": "Middle East Pharmaceutical Industries Co. Ltd. (MECP)",
        "legalStatusEn": "Prescription",
        "legalStatusAr": "يحتاج الى وصفة طبية ",
        "domainEN": "Human",
        "domainAR": "بشر",
        "imageUrl": null
    },
    {
        "id": 6952,
        "registerNumber": "30-437-16",
        "registerYear": 2016,
        "tradeName": "LYRGABA 75 mg capsule",
        "scientificName": "PREGABALIN",
        "atcCode1": "N03AX16",
        "atcCode2": "",
        "packageSize": 60,
        "size": 0,
        "strength": "75",
        "shelfLife": 24,
        "price": "128.4",
        "drugType": "Generic",
        "packageType": "Blister",
        "sizeUnit": null,
        "strengthUnit": "mg",
        "administrationRoute": "Oral",
        "doesageForm": "Capsule",
        "storageConditions": "store below 30°c",
        "marketingStatus": "Marketed",
        "legalStatus": "Prescription",
        "productControl": "Controlled",
        "productControlAr": "مقيد",
        "authorizationStatus": "Valid",
        "agent": "Middle East Pharmaceutical Industries Co. Ltd. (MECP)",
        "manufacturerName": "Middle East Pharmaceutical Industries Co. Ltd. (MECP)",
        "manufacturerCountry": "Saudi Arabia",
        "additionalManufacturer": null,
        "additionalManufacturerCountry": null,
        "companyName": "Middle East Pharmaceutical Industries Co. Ltd. (MECP)",
        "legalStatusEn": "Prescription",
        "legalStatusAr": "يحتاج الى وصفة طبية ",
        "domainEN": "Human",
        "domainAR": "بشر",
        "imageUrl": null
    },
    {
        "id": 6953,
        "registerNumber": "31-437-16",
        "registerYear": 2016,
        "tradeName": "LYRGABA 150 mg capsule",
        "scientificName": "PREGABALIN",
        "atcCode1": "N03AX16",
        "atcCode2": "",
        "packageSize": 40,
        "size": 0,
        "strength": "150",
        "shelfLife": 24,
        "price": "110.55",
        "drugType": "Generic",
        "packageType": "Blister",
        "sizeUnit": null,
        "strengthUnit": "mg",
        "administrationRoute": "Oral",
        "doesageForm": "Capsule",
        "storageConditions": "store below 30°c",
        "marketingStatus": "Marketed",
        "legalStatus": "Prescription",
        "productControl": "Controlled",
        "productControlAr": "مقيد",
        "authorizationStatus": "Valid",
        "agent": "Middle East Pharmaceutical Industries Co. Ltd. (MECP)",
        "manufacturerName": "Middle East Pharmaceutical Industries Co. Ltd. (MECP)",
        "manufacturerCountry": "Saudi Arabia",
        "additionalManufacturer": null,
        "additionalManufacturerCountry": null,
        "companyName": "Middle East Pharmaceutical Industries Co. Ltd. (MECP)",
        "legalStatusEn": "Prescription",
        "legalStatusAr": "يحتاج الى وصفة طبية ",
        "domainEN": "Human",
        "domainAR": "بشر",
        "imageUrl": null
    },
    {
        "id": 6955,
        "registerNumber": "32-437-16",
        "registerYear": 2016,
        "tradeName": "LYRGABA 150 mg capsule",
        "scientificName": "PREGABALIN",
        "atcCode1": "N03AX16",
        "atcCode2": "",
        "packageSize": 60,
        "size": 0,
        "strength": "150",
        "shelfLife": 24,
        "price": "165.8",
        "drugType": "Generic",
        "packageType": "Blister",
        "sizeUnit": null,
        "strengthUnit": "mg",
        "administrationRoute": "Oral",
        "doesageForm": "Capsule",
        "storageConditions": "store below 30°c",
        "marketingStatus": "Marketed",
        "legalStatus": "Prescription",
        "productControl": "Controlled",
        "productControlAr": "مقيد",
        "authorizationStatus": "Valid",
        "agent": "Middle East Pharmaceutical Industries Co. Ltd. (MECP)",
        "manufacturerName": "Middle East Pharmaceutical Industries Co. Ltd. (MECP)",
        "manufacturerCountry": "Saudi Arabia",
        "additionalManufacturer": null,
        "additionalManufacturerCountry": null,
        "companyName": "Middle East Pharmaceutical Industries Co. Ltd. (MECP)",
        "legalStatusEn": "Prescription",
        "legalStatusAr": "يحتاج الى وصفة طبية ",
        "domainEN": "Human",
        "domainAR": "بشر",
        "imageUrl": null
    },
    {
        "id": 3660,
        "registerNumber": "16-437-11",
        "registerYear": 2011,
        "tradeName": "AVOCOM 0.05% AQUEOUS NASAL SPRAY",
        "scientificName": "MOMETASONE FUROATE",
        "atcCode1": "R01AD09",
        "atcCode2": "",
        "packageSize": 1,
        "size": 120,
        "strength": "0.05",
        "shelfLife": 24,
        "price": "41.6",
        "drugType": "Generic",
        "packageType": "Nasal Applicator",
        "sizeUnit": null,
        "strengthUnit": "%",
        "administrationRoute": "Nasal",
        "doesageForm": "spray",
        "storageConditions": "store below 30°c",
        "marketingStatus": "Marketed",
        "legalStatus": "Prescription",
        "productControl": "Uncontrolled",
        "productControlAr": "غير مقيد",
        "authorizationStatus": "Valid",
        "agent": "Middle East Pharmaceutical Industries Co. Ltd. (MECP)",
        "manufacturerName": "Middle East Pharmaceutical Industries Co. Ltd. (MECP)",
        "manufacturerCountry": "Saudi Arabia",
        "additionalManufacturer": null,
        "additionalManufacturerCountry": null,
        "companyName": "Middle East Pharmaceutical Industries Co. Ltd. (MECP)",
        "legalStatusEn": "Prescription",
        "legalStatusAr": "يحتاج الى وصفة طبية ",
        "domainEN": "Human",
        "domainAR": "بشر",
        "imageUrl": null
    },
    {
        "id": 9549,
        "registerNumber": "61-437-19",
        "registerYear": 2019,
        "tradeName": "CORTRIEF NASAL SPRAY",
        "scientificName": "BUDESONIDE",
        "atcCode1": "R01AD05 ",
        "atcCode2": "",
        "packageSize": 1,
        "size": 6,
        "strength": "64",
        "shelfLife": 24,
        "price": "27.7",
        "drugType": "Generic",
        "packageType": "Spray Container",
        "sizeUnit": "ml",
        "strengthUnit": "µg",
        "administrationRoute": "Nasal",
        "doesageForm": "spray",
        "storageConditions": "store below 30°c",
        "marketingStatus": "Marketed",
        "legalStatus": "Prescription",
        "productControl": "Uncontrolled",
        "productControlAr": "غير مقيد",
        "authorizationStatus": "Valid",
        "agent": "Middle East Pharmaceutical Industries Co. Ltd. (MECP)",
        "manufacturerName": "Middle East Pharmaceutical Industries Co. Ltd. (MECP)",
        "manufacturerCountry": "Saudi Arabia",
        "additionalManufacturer": null,
        "additionalManufacturerCountry": null,
        "companyName": "Middle East Pharmaceutical Industries Co. Ltd. (MECP)",
        "legalStatusEn": "Prescription",
        "legalStatusAr": "يحتاج الى وصفة طبية ",
        "domainEN": "Human",
        "domainAR": "بشر",
        "imageUrl": null
    },
    {
        "id": 3602,
        "registerNumber": "9-437-08",
        "registerYear": 2008,
        "tradeName": "AVOTIN- A",
        "scientificName": "TRETINOIN",
        "atcCode1": "D10AD01",
        "atcCode2": "",
        "packageSize": 1,
        "size": 30,
        "strength": "0.05",
        "shelfLife": 24,
        "price": "15.9",
        "drugType": "Generic",
        "packageType": "Bottle",
        "sizeUnit": "g",
        "strengthUnit": "%",
        "administrationRoute": "Topical",
        "doesageForm": "cream",
        "storageConditions": "store below 25°c",
        "marketingStatus": "Marketed",
        "legalStatus": "Prescription",
        "productControl": "Uncontrolled",
        "productControlAr": "غير مقيد",
        "authorizationStatus": "Valid",
        "agent": "Middle East Pharmaceutical Industries Co. Ltd. (MECP)",
        "manufacturerName": "Middle East Pharmaceutical Industries Co. Ltd. (MECP)",
        "manufacturerCountry": "Saudi Arabia",
        "additionalManufacturer": null,
        "additionalManufacturerCountry": null,
        "companyName": "Middle East Pharmaceutical Industries Co. Ltd. (MECP)",
        "legalStatusEn": "Prescription",
        "legalStatusAr": "يحتاج الى وصفة طبية ",
        "domainEN": "Human",
        "domainAR": "بشر",
        "imageUrl": null
    },
    {
        "id": 6977,
        "registerNumber": "46-437-16",
        "registerYear": 2016,
        "tradeName": "AVOBAN 2% nasal ointment",
        "scientificName": "MUPIROCIN (PSEUDONOMIC ACID)",
        "atcCode1": "R01AX06",
        "atcCode2": "",
        "packageSize": 1,
        "size": 3,
        "strength": "2",
        "shelfLife": 24,
        "price": "28.45",
        "drugType": "Generic",
        "packageType": "Tube",
        "sizeUnit": "g",
        "strengthUnit": "%",
        "administrationRoute": "Nasal",
        "doesageForm": "ointment",
        "storageConditions": "store below 30°c",
        "marketingStatus": "Marketed",
        "legalStatus": "Prescription",
        "productControl": "Uncontrolled",
        "productControlAr": "غير مقيد",
        "authorizationStatus": "Valid",
        "agent": "Middle East Pharmaceutical Industries Co. Ltd. (MECP)",
        "manufacturerName": "Middle East Pharmaceutical Industries Co. Ltd. (MECP)",
        "manufacturerCountry": "Saudi Arabia",
        "additionalManufacturer": null,
        "additionalManufacturerCountry": null,
        "companyName": "Middle East Pharmaceutical Industries Co. Ltd. (MECP)",
        "legalStatusEn": "Prescription",
        "legalStatusAr": "يحتاج الى وصفة طبية ",
        "domainEN": "Human",
        "domainAR": "بشر",
        "imageUrl": null
    },
    {
        "id": 3319,
        "registerNumber": "12-437-10",
        "registerYear": 2010,
        "tradeName": "ADOLIN 0.1% W-W CREAM",
        "scientificName": "ADAPALENE",
        "atcCode1": "D10AD03",
        "atcCode2": "",
        "packageSize": 1,
        "size": 30,
        "strength": "0.1",
        "shelfLife": 24,
        "price": "16.25",
        "drugType": "Generic",
        "packageType": "Bottle",
        "sizeUnit": "g",
        "strengthUnit": "%",
        "administrationRoute": "Topical",
        "doesageForm": "cream",
        "storageConditions": "store below 25°c",
        "marketingStatus": "Marketed",
        "legalStatus": "Prescription",
        "productControl": "Uncontrolled",
        "productControlAr": "غير مقيد",
        "authorizationStatus": "Valid",
        "agent": "Middle East Pharmaceutical Industries Co. Ltd. (MECP)",
        "manufacturerName": "Middle East Pharmaceutical Industries Co. Ltd. (MECP)",
        "manufacturerCountry": "Saudi Arabia",
        "additionalManufacturer": null,
        "additionalManufacturerCountry": null,
        "companyName": "Middle East Pharmaceutical Industries Co. Ltd. (MECP)",
        "legalStatusEn": "Prescription",
        "legalStatusAr": "يحتاج الى وصفة طبية ",
        "domainEN": "Human",
        "domainAR": "بشر",
        "imageUrl": null
    }
]